{"P2": {"labels": ["Java"], "postTitle": "Mybatis\u4ee3\u7801\u751f\u6210\u5668Mybatis-Generator\u4f7f\u7528\u8be6\u89e3", "postUrl": "post/Mybatis-dai-ma-sheng-cheng-qi-Mybatis-Generator-shi-yong-xiang-jie.html", "createdDate": "2024-04-23", "dateLabelColor": "#bc4c00"}, "P1": {"labels": ["Java"], "postTitle": "Spring \u4e03\u79cd\u4e8b\u52a1\u4f20\u64ad\u6027\u4ecb\u7ecd", "postUrl": "post/Spring%20-qi-zhong-shi-wu-chuan-bo-xing-jie-shao.html", "createdDate": "2024-04-08", "dateLabelColor": "#bc4c00"}, "labelColorDict": {"documentation": "#0075ca", "Java": "#d4c5f9"}}